{
  "basic_info": {
    "short_form": "ESIC Hyderabad",
    "year_founded": 2016,
    "university_type": "",
    "type_of_college": "Public",
    "city": "Hyderabad",
    "state": "Telangana",
    "address": {
      "address": "7-1-634, Survey No.121/1 & 121/2, National Highway 65 Sanjeeva Reddy Nagar, Sanath Nagar India",
      "location": "",
      "nearest_bus_station": null,
      "nearest_train_station": null,
      "nearest_airport": null,
      "map_location": "ESIC Medical College Hospital",
      "pincode": "500038"
    },
    "landline": [
      {
        "value": "040-67872002",
        "text": ""
      },
      {
        "value": "040-67872017",
        "text": ""
      },
      {
        "value": "1800-11-2526",
        "text": ""
      },
      {
        "value": "011-23604700",
        "text": ""
      },
      {
        "value": "040-67872054",
        "text": ""
      }
    ],
    "mobile": [],
    "website": "https://mchyderabad.esic.gov.in/",
    "phone_no": [
      {
        "value": "040-67872002",
        "text": ""
      },
      {
        "value": "040-67872017",
        "text": ""
      },
      {
        "value": "1800-11-2526",
        "text": ""
      },
      {
        "value": "011-23604700",
        "text": ""
      },
      {
        "value": "040-67872054",
        "text": ""
      },
      null
    ],
    "approved_by": [
      "MCI"
    ],
    "major_stream_name": "Medical",
    "affiliated_to": {
      "name": "KNRUHS, Warangal"
    }
  },
  "courses": [
    {
      "course": "MBBS",
      "level": "Graduation",
      "duration_year": "5",
      "duration_month": "0",
      "stream": [],
      "eligibility": "10+2 with 50% + NEET",
      "course_type": "Full Time",
      "degree_type": "Degree",
      "short_head": "MBBS",
      "headone_data": {
        "headone": "mbbs",
        "type": "Full Time"
      },
      "fees_per_year": "1.17 Lakhs",
      "grand_total": "5.17 Lakhs"
    },
    {
      "course": "B.Sc",
      "level": "Graduation",
      "duration_year": "3",
      "duration_month": "0",
      "stream": [
        {
          "name": "Allied Health Sciences",
          "custom_name": "",
          "course_name": "Bachelor of Science [B.Sc] (Allied Health Sciences)",
          "display_course_name": "Bachelor of Science [B.Sc] (Allied Health Sciences)",
          "total_current_fee": {
            "general": {
              "amount": 55000,
              "year": "2025 - 2026"
            }
          }
        },
        {
          "name": "Medical Laboratory Technology",
          "custom_name": "",
          "course_name": "Bachelor of Science [B.Sc] (Medical Laboratory Technology)",
          "display_course_name": "Bachelor of Science [B.Sc] (Medical Laboratory Technology)",
          "total_current_fee": {
            "general": {
              "amount": 28500,
              "year": "2025 - 2026"
            }
          }
        }
      ],
      "eligibility": "10+2",
      "course_type": "Full Time",
      "degree_type": "Degree",
      "short_head": "B.Sc",
      "headone_data": {
        "headone": "bachelor-of-science-bsc",
        "type": "Full Time"
      },
      "caution_fee": [
        2500,
        0
      ],
      "library_fees": [
        4500,
        10500
      ],
      "fees_per_year": "9,500 - 20,000",
      "grand_total": "55,000"
    },
    {
      "course": "M.D",
      "level": "Post Graduation",
      "duration_year": "3",
      "duration_month": "0",
      "stream": [
        {
          "name": "Respiratory Medicine",
          "custom_name": "",
          "course_name": "Doctorate of Medicine [MD] (Respiratory Medicine)",
          "display_course_name": "Doctorate of Medicine [MD] (Respiratory Medicine)",
          "total_current_fee": {
            "general": {
              "amount": 750000,
              "year": "2024 - 2025"
            }
          }
        },
        {
          "name": "Anaesthesia",
          "custom_name": "",
          "course_name": "Doctorate of Medicine [MD] (Anaesthesia)",
          "display_course_name": "Doctorate of Medicine [MD] (Anaesthesia)",
          "total_current_fee": {
            "general": {
              "amount": 750000,
              "year": "2025 - 2026"
            }
          }
        },
        {
          "name": "Anatomy",
          "custom_name": "",
          "course_name": "Doctorate of Medicine [MD] (Anatomy)",
          "display_course_name": "Doctorate of Medicine [MD] (Anatomy)",
          "total_current_fee": {
            "general": {
              "amount": 750000,
              "year": "2024 - 2025"
            }
          }
        },
        {
          "name": "Biochemistry",
          "custom_name": "",
          "course_name": "Doctorate of Medicine [MD] (Biochemistry)",
          "display_course_name": "Doctorate of Medicine [MD] (Biochemistry)",
          "total_current_fee": {
            "general": {
              "amount": 750000,
              "year": "2024 - 2025"
            }
          }
        },
        {
          "name": "Community Medicine",
          "custom_name": "",
          "course_name": "Doctorate of Medicine [MD] (Community Medicine)",
          "display_course_name": "Doctorate of Medicine [MD] (Community Medicine)",
          "total_current_fee": {
            "general": {
              "amount": 750000,
              "year": "2024 - 2025"
            }
          }
        },
        {
          "name": "Dermatology, Venereology & Leprology",
          "custom_name": "",
          "course_name": "Doctorate of Medicine [MD] (Dermatology, Venereology & Leprology)",
          "display_course_name": "Doctorate of Medicine [MD] (Dermatology, Venereology & Leprology)",
          "total_current_fee": {
            "general": {
              "amount": 750000,
              "year": "2024 - 2025"
            }
          }
        },
        {
          "name": "Emergency Medicine",
          "custom_name": "",
          "course_name": "Doctorate of Medicine [MD] (Emergency Medicine)",
          "display_course_name": "Doctorate of Medicine [MD] (Emergency Medicine)",
          "total_current_fee": {
            "general": {
              "amount": 750000,
              "year": "2024 - 2025"
            }
          }
        },
        {
          "name": "General Medicine",
          "custom_name": "",
          "course_name": "Doctorate of Medicine [MD] (General Medicine)",
          "display_course_name": "Doctorate of Medicine [MD] (General Medicine)",
          "total_current_fee": {
            "general": {
              "amount": 750000,
              "year": "2024 - 2025"
            }
          }
        },
        {
          "name": "Microbiology",
          "custom_name": "",
          "course_name": "Doctorate of Medicine [MD] (Microbiology)",
          "display_course_name": "Doctorate of Medicine [MD] (Microbiology)",
          "total_current_fee": {
            "general": {
              "amount": 750000,
              "year": "2024 - 2025"
            }
          }
        },
        {
          "name": "Paediatrics",
          "custom_name": "",
          "course_name": "Doctorate of Medicine [MD] (Paediatrics)",
          "display_course_name": "Doctorate of Medicine [MD] (Paediatrics)",
          "total_current_fee": {
            "general": {
              "amount": 750000,
              "year": "2024 - 2025"
            }
          }
        },
        {
          "name": "Pathology",
          "custom_name": "",
          "course_name": "Doctorate of Medicine [MD] (Pathology)",
          "display_course_name": "Doctorate of Medicine [MD] (Pathology)",
          "total_current_fee": {
            "general": {
              "amount": 750000,
              "year": "2024 - 2025"
            }
          }
        },
        {
          "name": "Pharmacology",
          "custom_name": "",
          "course_name": "Doctorate of Medicine [MD] (Pharmacology)",
          "display_course_name": "Doctorate of Medicine [MD] (Pharmacology)",
          "total_current_fee": {
            "general": {
              "amount": 750000,
              "year": "2024 - 2025"
            }
          }
        },
        {
          "name": "Physical Medicine And Rehabilitation",
          "custom_name": "",
          "course_name": "Doctorate of Medicine [MD] (Physical Medicine and Rehabilitation)",
          "display_course_name": "Doctorate of Medicine [MD] (Physical Medicine and Rehabilitation)",
          "total_current_fee": {
            "general": {
              "amount": 750000,
              "year": "2024 - 2025"
            }
          }
        },
        {
          "name": "Physiology",
          "custom_name": "",
          "course_name": "Doctorate of Medicine [MD] (Physiology)",
          "display_course_name": "Doctorate of Medicine [MD] (Physiology)",
          "total_current_fee": {
            "general": {
              "amount": 750000,
              "year": "2024 - 2025"
            }
          }
        },
        {
          "name": "Psychiatry",
          "custom_name": "",
          "course_name": "Doctorate of Medicine [MD] (Psychiatry)",
          "display_course_name": "Doctorate of Medicine [MD] (Psychiatry)",
          "total_current_fee": {
            "general": {
              "amount": 750000,
              "year": "2024 - 2025"
            }
          }
        },
        {
          "name": "Radiodiagnosis",
          "custom_name": "",
          "course_name": "Doctorate of Medicine [MD] (Radiodiagnosis)",
          "display_course_name": "Doctorate of Medicine [MD] (Radiodiagnosis)",
          "total_current_fee": {
            "general": {
              "amount": 750000,
              "year": "2024 - 2025"
            }
          }
        },
        {
          "name": "Transfusion Medicine",
          "custom_name": "",
          "course_name": "Doctorate of Medicine [MD] (Transfusion Medicine)",
          "display_course_name": "Doctorate of Medicine [MD] (Transfusion Medicine)",
          "total_current_fee": {
            "general": {
              "amount": 750000,
              "year": "2024 - 2025"
            }
          }
        }
      ],
      "eligibility": "MBBS + NEET PG",
      "course_type": "Full Time",
      "degree_type": "Post Graduation",
      "short_head": "M.D",
      "headone_data": {
        "headone": "doctorate-of-medicine-md",
        "type": "Full Time"
      },
      "fees_per_year": "2.5 Lakhs",
      "grand_total": "7.5 Lakhs"
    },
    {
      "course": "M.Ch",
      "level": "Post Graduation",
      "duration_year": "3",
      "duration_month": "0",
      "stream": [
        {
          "name": "Plastic and Reconstructive Surgery",
          "custom_name": "",
          "course_name": "Master of Chirurgiae [M.Ch] (Plastic and Reconstructive Surgery)",
          "display_course_name": "Master of Chirurgiae [M.Ch] (Plastic and Reconstructive Surgery)",
          "total_current_fee": {
            "general": {
              "amount": 805000,
              "year": "2024 - 2025"
            }
          }
        },
        {
          "name": "Cardio-Vascular Thoracic Surgery",
          "custom_name": "",
          "course_name": "Master of Chirurgiae [M.Ch] (Cardio-Vascular Thoracic Surgery)",
          "display_course_name": "Master of Chirurgiae [M.Ch] (Cardio-Vascular Thoracic Surgery)",
          "total_current_fee": {
            "general": {
              "amount": 805000,
              "year": "2025 - 2026"
            }
          }
        },
        {
          "name": "Neuro Surgery",
          "custom_name": "",
          "course_name": "Master of Chirurgiae [M.Ch] (Neuro Surgery)",
          "display_course_name": "Master of Chirurgiae [M.Ch] (Neuro Surgery)",
          "total_current_fee": {
            "general": {
              "amount": 805000,
              "year": "2024 - 2025"
            }
          }
        },
        {
          "name": "Paediatric Surgery",
          "custom_name": "",
          "course_name": "Master of Chirurgiae [M.Ch] (Paediatric Surgery)",
          "display_course_name": "Master of Chirurgiae [M.Ch] (Paediatric Surgery)",
          "total_current_fee": {
            "general": {
              "amount": 805000,
              "year": "2024 - 2025"
            }
          }
        },
        {
          "name": "Urology",
          "custom_name": "",
          "course_name": "Master of Chirurgiae [M.Ch] (Urology)",
          "display_course_name": "Master of Chirurgiae [M.Ch] (Urology)",
          "total_current_fee": {
            "general": {
              "amount": 805000,
              "year": "2024 - 2025"
            }
          }
        }
      ],
      "eligibility": "MBBS+NEET SS",
      "course_type": "Full Time",
      "degree_type": "Post Graduation",
      "short_head": "M.Ch",
      "headone_data": {
        "headone": "master-of-chirurgiae-mch",
        "type": "Full Time"
      },
      "caution_fee": [
        5000,
        5000,
        5000,
        5000,
        5000
      ],
      "university_fees": [
        45000,
        45000,
        45000,
        45000,
        45000
      ],
      "fees_per_year": "3.05 Lakhs",
      "grand_total": "8.05 Lakhs"
    },
    {
      "course": "Associate Fellow of Industrial Health [AFIH]",
      "level": "Graduation",
      "duration_year": "0",
      "duration_month": "3",
      "stream": [],
      "eligibility": "MD/MS/DNB/Diploma",
      "course_type": "Full Time",
      "degree_type": "Diploma",
      "short_head": "AFIH",
      "headone_data": {
        "headone": "associate-fellow",
        "type": "Full Time"
      },
      "total_fees": "25,000",
      "grand_total": "25,000"
    },
    {
      "course": "M.S",
      "level": "Post Graduation",
      "duration_year": "3",
      "duration_month": "0",
      "stream": [
        {
          "name": "E.N.T.",
          "custom_name": "",
          "course_name": "Master of Surgery [M.S] (E.N.T.)",
          "display_course_name": "Master of Surgery [M.S] (E.N.T.)",
          "total_current_fee": {
            "general": {
              "amount": 750000,
              "year": "2025 - 2026"
            }
          }
        },
        {
          "name": "Obstetrics & Gynaecology",
          "custom_name": "",
          "course_name": "Master of Surgery [M.S] (Obstetrics & Gynaecology)",
          "display_course_name": "Master of Surgery [M.S] (Obstetrics & Gynaecology)",
          "total_current_fee": {
            "general": {
              "amount": 750000,
              "year": "2024 - 2025"
            }
          }
        },
        {
          "name": "Orthopaedics",
          "custom_name": "",
          "course_name": "Master of Surgery [M.S] (Orthopaedics)",
          "display_course_name": "Master of Surgery [M.S] (Orthopaedics)",
          "total_current_fee": {
            "general": {
              "amount": 750000,
              "year": "2024 - 2025"
            }
          }
        }
      ],
      "eligibility": "MBBS + NEETPG",
      "course_type": "Full Time",
      "degree_type": "Post Graduation",
      "short_head": "M.S",
      "headone_data": {
        "headone": "master-of-surgery-ms",
        "type": "Full Time"
      },
      "fees_per_year": "2.5 Lakhs",
      "grand_total": "7.5 Lakhs"
    },
    {
      "course": "M.S",
      "level": "Post Graduation",
      "duration_year": "3",
      "duration_month": "0",
      "stream": [
        {
          "name": "General Surgery",
          "custom_name": "",
          "course_name": "Master of Surgery [MS] (General Surgery)",
          "display_course_name": "Master of Surgery [MS] (General Surgery)",
          "total_current_fee": {
            "general": {
              "amount": 750000,
              "year": "2024 - 2025"
            }
          }
        },
        {
          "name": "Ophthalmology",
          "custom_name": "",
          "course_name": "Master of Surgery [MS] (Ophthalmology)",
          "display_course_name": "Master of Surgery [MS] (Ophthalmology)",
          "total_current_fee": {
            "general": {
              "amount": 750000,
              "year": "2024 - 2025"
            }
          }
        }
      ],
      "eligibility": "MBBS + NEET PG",
      "course_type": "Full Time",
      "degree_type": "Post Graduation",
      "short_head": "M.S",
      "headone_data": {
        "headone": "master-of-surgey-ms",
        "type": "Full Time"
      },
      "fees_per_year": "2.5 Lakhs",
      "grand_total": "7.5 Lakhs"
    },
    {
      "course": "DNB",
      "level": "Doctorate/M.Phil",
      "duration_year": "3",
      "duration_month": "0",
      "stream": [
        {
          "name": "Endocrinology",
          "custom_name": "",
          "course_name": "Diplomate National Board [DNB] (Endocrinology)",
          "display_course_name": "Diplomate National Board [DNB] (Endocrinology)",
          "total_current_fee": {
            "general": {
              "amount": 805000,
              "year": "2025 - 2026"
            }
          }
        },
        {
          "name": "Family Medicine",
          "custom_name": "",
          "course_name": "Diplomate National Board [DNB] (Family Medicine)",
          "display_course_name": "Diplomate National Board [DNB] (Family Medicine)",
          "total_current_fee": {
            "general": {
              "amount": 375000,
              "year": "2025 - 2026"
            }
          }
        },
        {
          "name": "Medical Oncology",
          "custom_name": "",
          "course_name": "Diplomate National Board [DNB] (Medical Oncology)",
          "display_course_name": "Diplomate National Board [DNB] (Medical Oncology)",
          "total_current_fee": {
            "general": {
              "amount": 805000,
              "year": "2024 - 2025"
            }
          }
        },
        {
          "name": "Nephrology",
          "custom_name": "",
          "course_name": "Diplomate National Board [DNB] (Nephrology)",
          "display_course_name": "Diplomate National Board [DNB] (Nephrology)",
          "total_current_fee": {
            "general": {
              "amount": 805000,
              "year": "2024 - 2025"
            }
          }
        },
        {
          "name": "Neurology",
          "custom_name": "",
          "course_name": "Diplomate National Board [DNB] (Neurology)",
          "display_course_name": "Diplomate National Board [DNB] (Neurology)",
          "total_current_fee": {
            "general": {
              "amount": 805000,
              "year": "2024 - 2025"
            }
          }
        },
        {
          "name": "Rheumatology",
          "custom_name": "",
          "course_name": "Diplomate National Board [DNB] (Rheumatology)",
          "display_course_name": "Diplomate National Board [DNB] (Rheumatology)",
          "total_current_fee": {
            "general": {
              "amount": 805000,
              "year": "2024 - 2025"
            }
          }
        }
      ],
      "eligibility": "MBBS+NEET SS",
      "course_type": "Full Time",
      "degree_type": "Degree",
      "short_head": "DNB",
      "headone_data": {
        "headone": "diplomate-national-board-dnb",
        "type": "Full Time"
      },
      "caution_fee": [
        5000,
        0,
        5000,
        5000,
        5000,
        5000
      ],
      "university_fees": [
        45000,
        0,
        45000,
        45000,
        45000,
        45000
      ],
      "fees_per_year": "1.25 Lakhs - 3.05 Lakhs",
      "grand_total": "8.05 Lakhs"
    }
  ]
}