{
  "basic_info": {
    "short_form": "Kishinchand Chellaram College",
    "year_founded": 1954,
    "university_type": "",
    "type_of_college": "Public",
    "city": "Mumbai",
    "state": "Maharashtra",
    "address": {
      "address": "Vidyasagar Principal K.M. Kundnani Chowk, 124, Dinshaw Wachha Road, Churchgate, India",
      "location": "#124, Dinshaw Wachha Road, Churchgate",
      "nearest_bus_station": {
        "name": "Mantralaya",
        "lat": 18.928381,
        "lon": 72.824484,
        "place_id": "ChIJ6yN-8OjR5zsR7pBqgo-ahj8",
        "distance": 420,
        "eta": 169
      },
      "nearest_train_station": null,
      "nearest_airport": {
        "name": "Taj Wellington Mews Helipad",
        "lat": 18.9218829,
        "lon": 72.8286012,
        "place_id": "ChIJZ4sxLsDR5zsRqUIKYHsPyQk",
        "distance": 1065,
        "eta": 252
      },
      "map_location": "Kishinchand Chellaram College",
      "pincode": "400020"
    },
    "landline": [
      {
        "value": "022-22855726",
        "text": ""
      },
      {
        "value": 66981000,
        "text": ""
      },
      {
        "value": 66981025,
        "text": "Principal"
      }
    ],
    "mobile": [
      "9821316803"
    ],
    "website": "http://www.kccollege.edu.in/",
    "phone_no": [
      {
        "value": "022-22855726",
        "text": ""
      },
      {
        "value": 66981000,
        "text": ""
      },
      {
        "value": 66981025,
        "text": "Principal"
      },
      "9821316803"
    ],
    "approved_by": [],
    "major_stream_name": "Science",
    "affiliated_to": {
      "name": "HSNC University Mumbai, Mumbai"
    }
  },
  "courses": [
    {
      "course": "B.Sc",
      "level": "Graduation",
      "duration_year": "3",
      "duration_month": "0",
      "stream": [
        {
          "name": "Data Science and Business Analytics",
          "custom_name": "",
          "course_name": "Bachelor of Science [B.Sc] (Data Science and Business Analytics)",
          "display_course_name": "Bachelor of Science [B.Sc] (Data Science and Business Analytics)",
          "total_current_fee": null
        },
        {
          "name": "Information Technology",
          "custom_name": "",
          "course_name": "Bachelor of Science [B.Sc] (Information Technology)",
          "display_course_name": "Bachelor of Science [B.Sc] (Information Technology)",
          "total_current_fee": {
            "general": {
              "amount": 104535,
              "year": "2022 - 2023"
            }
          }
        },
        {
          "name": "Computer Science",
          "custom_name": "",
          "course_name": "Bachelor of Science [B.Sc] (Computer Science)",
          "display_course_name": "Bachelor of Science [B.Sc] (Computer Science)",
          "total_current_fee": {
            "general": {
              "amount": 104535,
              "year": "2022 - 2023"
            }
          }
        },
        {
          "name": "Biotechnology",
          "custom_name": "",
          "course_name": "Bachelor of Science [B.Sc] (Biotechnology)",
          "display_course_name": "Bachelor of Science [B.Sc] (Biotechnology)",
          "total_current_fee": {
            "general": {
              "amount": 104535,
              "year": "2022 - 2023"
            }
          }
        },
        {
          "name": "Microbiology",
          "custom_name": "",
          "course_name": "Bachelor of Science [B.Sc] (Microbiology)",
          "display_course_name": "Bachelor of Science [B.Sc] (Microbiology)",
          "total_current_fee": {
            "general": {
              "amount": 24965,
              "year": "2020 - 2021"
            },
            "sc/st": {
              "amount": 14065,
              "year": "2020 - 2021"
            }
          }
        },
        {
          "name": "General",
          "custom_name": "",
          "course_name": "Bachelor of Science [B.Sc]",
          "display_course_name": "Bachelor of Science [B.Sc]",
          "total_current_fee": {
            "general": {
              "amount": 26460,
              "year": "2022 - 2023"
            }
          }
        },
        {
          "name": "Life Sciences",
          "custom_name": "",
          "course_name": "Bachelor of Science [B.Sc] (Life Sciences)",
          "display_course_name": "Bachelor of Science [B.Sc] (Life Sciences)",
          "total_current_fee": {
            "general": {
              "amount": 24965,
              "year": "2020 - 2021"
            },
            "sc/st": {
              "amount": 14065,
              "year": "2020 - 2021"
            }
          }
        },
        {
          "name": "Statistics",
          "custom_name": "",
          "course_name": "Bachelor of Science [B.Sc] (Statistics)",
          "display_course_name": "Bachelor of Science [B.Sc] (Statistics)",
          "total_current_fee": {
            "general": {
              "amount": 24965,
              "year": "2020 - 2021"
            },
            "sc/st": {
              "amount": 14065,
              "year": "2020 - 2021"
            }
          }
        },
        {
          "name": "Mathematics",
          "custom_name": "",
          "course_name": "Bachelor of Science [B.Sc] (Mathematics)",
          "display_course_name": "Bachelor of Science [B.Sc] (Mathematics)",
          "total_current_fee": {
            "general": {
              "amount": 24965,
              "year": "2020 - 2021"
            },
            "sc/st": {
              "amount": 14065,
              "year": "2020 - 2021"
            }
          }
        },
        {
          "name": "Chemistry",
          "custom_name": "",
          "course_name": "Bachelor of Science [B.Sc] (Chemistry)",
          "display_course_name": "Bachelor of Science [B.Sc] (Chemistry)",
          "total_current_fee": {
            "general": {
              "amount": 24965,
              "year": "2020 - 2021"
            },
            "sc/st": {
              "amount": 14065,
              "year": "2020 - 2021"
            }
          }
        },
        {
          "name": "Physics",
          "custom_name": "",
          "course_name": "Bachelor of Science [B.Sc] (Physics)",
          "display_course_name": "Bachelor of Science [B.Sc] (Physics)",
          "total_current_fee": {
            "general": {
              "amount": 24965,
              "year": "2020 - 2021"
            },
            "sc/st": {
              "amount": 14065,
              "year": "2020 - 2021"
            }
          }
        }
      ],
      "eligibility": "10+2",
      "course_type": "Full Time",
      "degree_type": "Degree",
      "short_head": "B.Sc",
      "headone_data": {
        "headone": "bachelor-of-science-bsc",
        "type": "Full Time"
      },
      "admission_fee": [
        0,
        0,
        0,
        0,
        200,
        0,
        200,
        200,
        200,
        200,
        200
      ],
      "other_fee": [
        0,
        0,
        0,
        0,
        19865,
        0,
        19865,
        19865,
        19865,
        19865,
        19865
      ],
      "fees_per_year": "8,820 - 34,845",
      "grand_total": "24,965"
    },
    {
      "course": "MA",
      "level": "Post Graduation",
      "duration_year": "2",
      "duration_month": "0",
      "stream": [
        {
          "name": "Psychology",
          "custom_name": "",
          "course_name": "Master of Arts [MA] (Psychology)",
          "display_course_name": "Master of Arts [MA] (Psychology)",
          "total_current_fee": {
            "general": {
              "amount": 63920,
              "year": ""
            }
          }
        },
        {
          "name": "Mass Communication & Journalism",
          "custom_name": "",
          "course_name": "Master of Arts [MA] (Mass Communication & Journalism)",
          "display_course_name": "Master of Arts [MA] (Mass Communication & Journalism)",
          "total_current_fee": {
            "sc/st": {
              "amount": 115920,
              "year": "2020 - 2021"
            }
          }
        },
        {
          "name": "Entertainment, Media And Advertising",
          "custom_name": "",
          "course_name": "Master of Arts [M.A.] (Entertainment, Media and Advertising)",
          "display_course_name": "Master of Arts [M.A.] (Entertainment, Media and Advertising)",
          "total_current_fee": {
            "general": {
              "amount": 124840,
              "year": "2020 - 2021"
            }
          }
        },
        {
          "name": "Economics",
          "custom_name": "",
          "course_name": "Master of Arts [MA] (Economics)",
          "display_course_name": "Master of Arts [MA] (Economics)",
          "total_current_fee": null
        },
        {
          "name": "Hindi",
          "custom_name": "",
          "course_name": "Master of Arts [MA] (Hindi)",
          "display_course_name": "Master of Arts [MA] (Hindi)",
          "total_current_fee": {
            "general": {
              "amount": 49840,
              "year": "2020 - 2021"
            }
          }
        }
      ],
      "eligibility": "Graduation",
      "course_type": "Full Time",
      "degree_type": "Post Graduation",
      "short_head": "MA",
      "headone_data": {
        "headone": "master-of-arts-ma",
        "type": "Full Time"
      },
      "admission_fee": [
        1000,
        1000,
        1000,
        0,
        2000
      ],
      "other_fee": [
        42920,
        30920,
        31840,
        0,
        31840
      ],
      "fees_per_year": "24,920 - 62,920",
      "grand_total": "1.25 Lakhs"
    },
    {
      "course": "Bachelor of Management Studies [BMS]",
      "level": "Graduation",
      "duration_year": "3",
      "duration_month": "0",
      "stream": [],
      "eligibility": "10+2",
      "course_type": "Full Time",
      "degree_type": "Degree",
      "short_head": "BMS",
      "headone_data": {
        "headone": "bachelor-of-management-studies-bms",
        "type": "Full Time"
      },
      "fees_per_year": "39,945",
      "grand_total": "1.2 Lakhs"
    },
    {
      "course": "M.Sc",
      "level": "Post Graduation",
      "duration_year": "2",
      "duration_month": "0",
      "stream": [
        {
          "name": "Information Technology",
          "custom_name": "",
          "course_name": "Master of Science [M.Sc.] (Information Technology)",
          "display_course_name": "Master of Science [M.Sc.] (Information Technology)",
          "total_current_fee": {
            "general": {
              "amount": 93920,
              "year": "2020 - 2021"
            }
          }
        },
        {
          "name": "Computer Science",
          "custom_name": "",
          "course_name": "Master of Science [M.Sc] (Computer Science)",
          "display_course_name": "Master of Science [M.Sc] (Computer Science)",
          "total_current_fee": {
            "general": {
              "amount": 99920,
              "year": "2020 - 2021"
            }
          }
        },
        {
          "name": "Microbiology",
          "custom_name": "",
          "course_name": "Master of Science [M.Sc] (Microbiology)",
          "display_course_name": "Master of Science [M.Sc] (Microbiology)",
          "total_current_fee": null
        },
        {
          "name": "Chemistry",
          "custom_name": "",
          "course_name": "Master of Science [M.Sc] (Chemistry)",
          "display_course_name": "Master of Science [M.Sc] (Chemistry)",
          "total_current_fee": null
        }
      ],
      "eligibility": "Graduation",
      "course_type": "Full Time",
      "degree_type": "Post Graduation",
      "short_head": "M.Sc",
      "headone_data": {
        "headone": "master-of-science-msc",
        "type": "Full Time"
      },
      "admission_fee": [
        1000,
        1000,
        0,
        0
      ],
      "other_fee": [
        60920,
        58920,
        0,
        0
      ],
      "fees_per_year": "47,920 - 50,920",
      "grand_total": "99,920"
    },
    {
      "course": "B.M.M",
      "level": "Graduation",
      "duration_year": "3",
      "duration_month": "0",
      "stream": [],
      "eligibility": "10+2",
      "course_type": "Full Time",
      "degree_type": "Degree",
      "short_head": "B.M.M",
      "headone_data": {
        "headone": "bachelor-of-mass-media-bmm",
        "type": "Full Time"
      },
      "fees_per_year": "36,345",
      "grand_total": "1.09 Lakhs"
    },
    {
      "course": "Bachelor of Commerce [B.Com]",
      "level": "Graduation",
      "duration_year": "3",
      "duration_month": "0",
      "stream": [],
      "eligibility": "10+2",
      "course_type": "Full Time",
      "degree_type": "Degree",
      "short_head": "B.Com",
      "headone_data": {
        "headone": "bachelor-of-commerce-bcom",
        "type": "Full Time"
      },
      "fees_per_year": "9,820",
      "grand_total": "29,460"
    },
    {
      "course": "BA",
      "level": "Graduation",
      "duration_year": "3",
      "duration_month": "0",
      "stream": [
        {
          "name": "Film, Television and New Media Production",
          "custom_name": "",
          "course_name": "Bachelor of Arts [BA] (Film, Television and New Media Production)",
          "display_course_name": "Bachelor of Arts [BA] (Film, Television and New Media Production)",
          "total_current_fee": {
            "general": {
              "amount": 29460,
              "year": "2022 - 2023"
            }
          }
        },
        {
          "name": "General",
          "custom_name": "",
          "course_name": "Bachelor of Arts [BA]",
          "display_course_name": "Bachelor of Arts [BA]",
          "total_current_fee": {
            "general": {
              "amount": 29460,
              "year": "2022 - 2023"
            }
          }
        }
      ],
      "eligibility": "10+2",
      "course_type": "Full Time",
      "degree_type": "Degree",
      "short_head": "BA",
      "headone_data": {
        "headone": "bachelor-of-arts-ba",
        "type": "Full Time"
      },
      "fees_per_year": "9,820",
      "grand_total": "29,460"
    },
    {
      "course": "Bachelor of Commerce with Banking and Insurance [BBI]",
      "level": "Graduation",
      "duration_year": "3",
      "duration_month": "0",
      "stream": [],
      "eligibility": "10+2",
      "course_type": "Full Time",
      "degree_type": "Degree",
      "short_head": "BBI",
      "headone_data": {
        "headone": "bachelor-of-commerce-with-banking-and-insurance-bbi",
        "type": "Full Time"
      },
      "admission_fee": [
        200
      ],
      "other_fee": [
        42890
      ],
      "fees_per_year": "35,610",
      "grand_total": "1.05 Lakhs"
    },
    {
      "course": "Master of Commerce [M.Com] (Advanced Accountancy)",
      "level": "Post Graduation",
      "duration_year": "2",
      "duration_month": "0",
      "stream": [],
      "eligibility": "Graduation",
      "course_type": "Full Time",
      "degree_type": "Post Graduation",
      "short_head": "M.Com",
      "headone_data": {
        "headone": "master-of-commerce-mcom",
        "type": "Full Time"
      },
      "admission_fee": [
        1000
      ],
      "other_fee": [
        30920
      ],
      "fees_per_year": "32,920",
      "grand_total": "63,920"
    },
    {
      "course": "Master of Science [M.S] (Research)",
      "level": "Post Graduation",
      "duration_year": "3",
      "duration_month": "0",
      "stream": [],
      "eligibility": "Graduation",
      "course_type": "Full Time",
      "degree_type": "Post Graduation",
      "short_head": "M.S",
      "headone_data": {
        "headone": "master-of-science-ms",
        "type": "Full Time"
      },
      "admission_fee": [
        1000
      ],
      "other_fee": [
        66920
      ],
      "fees_per_year": "33,920",
      "grand_total": "77,920"
    }
  ]
}