{
  "basic_info": {
    "short_form": "Trident B.Ed. College",
    "year_founded": 2010,
    "university_type": "",
    "type_of_college": "Private",
    "city": "Bhojpur",
    "state": "Bihar",
    "address": {
      "address": "Giddha Industrial Growth Centre India",
      "location": "Giddha Industrial Growth Center, Gidha, Ara",
      "nearest_bus_station": null,
      "nearest_train_station": null,
      "nearest_airport": null,
      "map_location": "Trident B.Ed. College, Bhojpur",
      "pincode": "802314"
    },
    "landline": [
      {
        "value": "06182-277119",
        "text": ""
      }
    ],
    "mobile": [
      "952http://betacontent.collegedunia.com/college/23448/edit#5135770",
      "8406004619",
      "8406004620"
    ],
    "website": "http://tridentbedcollege.co.in/",
    "phone_no": [
      {
        "value": "06182-277119",
        "text": ""
      },
      "952http://betacontent.collegedunia.com/college/23448/edit#5135770",
      "8406004619",
      "8406004620"
    ],
    "approved_by": [
      "NCTE"
    ],
    "major_stream_name": "Education",
    "affiliated_to": {
      "name": "AKU, Patna"
    }
  },
  "courses": [
    {
      "course": "Bachelor of Education [B.Ed]",
      "level": "Graduation",
      "duration_year": "2",
      "duration_month": "0",
      "stream": [],
      "eligibility": "Graduation",
      "course_type": "Full Time",
      "degree_type": "Degree",
      "short_head": "B.Ed",
      "headone_data": {
        "headone": "bachelor-of-education-bed",
        "type": "Full Time"
      },
      "total_fees": "1.5 Lakhs",
      "grand_total": "1.5 Lakhs"
    }
  ]
}