{
  "name": "Government Medical College Manjeri",
  "aka": [
    "GMC Manjeri"
  ],
  "state": "Kerala",
  "district": "Malappuram District",
  "city": "Manjeri",
  "address": null,
  "contacts": {
    "phone": [
      "04832766425",
      "04832764056"
    ],
    "email": [],
    "website": "http://gmc-manjeri.weebly.com/"
  },
  "accreditations": [
    {
      "name": "Medical Council Of India",
      "status": "Accredited",
      "since": null
    }
  ],
  "affiliations": [
    "Kerala University of Health Sciences (KUSH)"
  ],
  "courses": [
    {
      "title": "M.B.B.S.",
      "name": "M.B.B.S.",
      "specialization": "",
      "stream": "General",
      "type": "Undergraduate",
      "duration": "5 years",
      "fees": {
        "from": "23",
        "to": "23150"
      },
      "entrance_exams": "",
      "seats": null
    },
    {
      "title": "Doctorate of Medicine [MD] (Dermatology, Venereology & Leprology) - Dermatology, Venereology & Leprology",
      "name": "Doctorate of Medicine [MD] (Dermatology, Venereology & Leprology)",
      "specialization": "Dermatology, Venereology & Leprology",
      "stream": "Medical",
      "type": "Postgraduate",
      "duration": "3 years",
      "fees": {
        "from": "1",
        "to": "64410"
      },
      "entrance_exams": "",
      "seats": null
    },
    {
      "title": "Master of Surgery [MS] (Ophthalmology) - Ophthalmology",
      "name": "Master of Surgery [MS] (Ophthalmology)",
      "specialization": "Ophthalmology",
      "stream": "General",
      "type": "Postgraduate",
      "duration": "3 years",
      "fees": {
        "from": "0",
        "to": "74000"
      },
      "entrance_exams": "",
      "seats": null
    },
    {
      "title": "Master of Surgery [M.S] (E.N.T.) - E.N.T.",
      "name": "Master of Surgery [M.S] (E.N.T.)",
      "specialization": "E.N.T.",
      "stream": "General",
      "type": "Postgraduate",
      "duration": "3 years",
      "fees": {
        "from": "0",
        "to": "74000"
      },
      "entrance_exams": "",
      "seats": null
    },
    {
      "title": "Bachelor of Dental Surgery [BDS] - BDS",
      "name": "Bachelor of Dental Surgery [BDS]",
      "specialization": "BDS",
      "stream": "Medical",
      "type": "Undergraduate",
      "duration": "3 years",
      "fees": {
        "from": "20",
        "to": "20840"
      },
      "entrance_exams": "",
      "seats": null
    },
    {
      "title": "MBBS",
      "name": "MBBS",
      "specialization": "",
      "stream": "Medical",
      "type": "Undergraduate",
      "duration": "3 years",
      "fees": {
        "from": "23",
        "to": "23150"
      },
      "entrance_exams": "",
      "seats": null
    },
    {
      "title": "BDS",
      "name": "BDS",
      "specialization": "",
      "stream": "Medical",
      "type": "Undergraduate",
      "duration": "3 years",
      "fees": {
        "from": "20",
        "to": "20840"
      },
      "entrance_exams": "",
      "seats": null
    }
  ],
  "entrance_exams": [
    {
      "name": "NEET UG",
      "status": "Required",
      "since": null
    }
  ],
  "rankings": [],
  "campus_size": null,
  "fees": {
    "from": null,
    "to": null
  },
  "placements": [],
  "notable_alumni": [],
  "enrichment_score": 4,
  "url": "https://collegedunia.com/college/55336-government-medical-college-gmc-manjeri-malappuram",
  "enrichment_metadata": {
    "processed_at": "2025-09-14T17:40:16.187745",
    "courses_before": 1,
    "courses_after": 7,
    "improvement_score": 6,
    "standardization_applied": true,
    "crawler_version": "corrected_v2",
    "standardizer_version": "v1.0"
  }
}