{
  "basic_info": {
    "short_form": "MM Institute of Hotel Management and Catering Technology",
    "year_founded": 2002,
    "university_type": "",
    "type_of_college": "Private",
    "city": "Ambala",
    "state": "Haryana",
    "address": {
      "address": "Mullana India",
      "location": "Mullana",
      "nearest_bus_station": {
        "name": "Polytechnic Bus Stop",
        "lat": 30.379247,
        "lon": 76.778263,
        "place_id": "ChIJmzShP_XIDzkROeT_spkJvcE",
        "distance": 252,
        "eta": 83
      },
      "nearest_train_station": {
        "name": "UBC/Ambala City",
        "lat": 30.377902,
        "lon": 76.764463,
        "place_id": "ChIJqViPrezIDzkRS960iWojEPM",
        "distance": 3285,
        "eta": 549
      },
      "nearest_airport": null,
      "map_location": "Maharishi Markandeshwar (Deemed to be University)",
      "pincode": "133207"
    },
    "landline": [
      {
        "value": 18002740240,
        "text": "Toll Free"
      },
      {
        "value": "01731-274475",
        "text": ""
      },
      {
        "value": 274477,
        "text": ""
      }
    ],
    "mobile": [
      "8059930001",
      "8059930002",
      "8059930003"
    ],
    "website": "http://www.mmumullana.org/hotel-management",
    "phone_no": [
      {
        "value": 18002740240,
        "text": "Toll Free"
      },
      {
        "value": "01731-274475",
        "text": ""
      },
      {
        "value": 274477,
        "text": ""
      },
      "8059930001",
      "8059930002",
      "8059930003"
    ],
    "approved_by": [
      "AICTE"
    ],
    "major_stream_name": "Hotel Management"
  },
  "courses": [
    {
      "course": "B.Sc Honours",
      "level": "Graduation",
      "duration_year": "4",
      "duration_month": "0",
      "stream": [
        {
          "name": "Food Technology",
          "custom_name": "",
          "course_name": "Bachelor of Science [B.Sc] Honours (Food Technology)",
          "display_course_name": "Bachelor of Science [B.Sc] Honours (Food Technology)",
          "total_current_fee": {
            "general": {
              "amount": 172000,
              "year": "2024 - 2025"
            }
          }
        },
        {
          "name": "Hospitality and Hotel Administration",
          "custom_name": "",
          "course_name": "Bachelor of Science [B.Sc] Honours (Hospitality and Hotel Administration)",
          "display_course_name": "Bachelor of Science [B.Sc] Honours (Hospitality and Hotel Administration)",
          "total_current_fee": {
            "general": {
              "amount": 231000,
              "year": "2024 - 2025"
            }
          }
        },
        {
          "name": "Nutrition & Dietetics",
          "custom_name": "",
          "course_name": "Bachelor of Science [B.Sc] Honours (Nutrition & Dietetics)",
          "display_course_name": "Bachelor of Science [B.Sc] Honours (Nutrition & Dietetics)",
          "total_current_fee": {
            "general": {
              "amount": 172000,
              "year": "2024 - 2025"
            }
          }
        }
      ],
      "eligibility": "10+2 with 50%+CUET",
      "course_type": "Full Time",
      "degree_type": "Degree",
      "short_head": "B.Sc {Hons.}",
      "headone_data": {
        "headone": "bachelor-of-science-bsc-hons",
        "type": "Full Time"
      },
      "development_fees": [
        0,
        7000,
        0
      ],
      "alumni_fees": [
        4000,
        4000,
        4000
      ],
      "fees_per_year": "46,000 - 66,000",
      "grand_total": "1.72 Lakhs"
    },
    {
      "course": "BHMCT",
      "level": "Graduation",
      "duration_year": "4",
      "duration_month": "0",
      "stream": [],
      "eligibility": "10+2 with 50%",
      "course_type": "Full Time",
      "degree_type": "Degree",
      "short_head": "BHMCT",
      "headone_data": {
        "headone": "bachelor-of-hotel-management-and-catering-technology-bhmct",
        "type": "Full Time"
      },
      "fees_per_year": "66,000",
      "grand_total": "2.31 Lakhs"
    },
    {
      "course": "Diploma",
      "level": "10+2",
      "duration_year": "1",
      "duration_month": "6",
      "stream": [
        {
          "name": "Airlines, Tourism & Hospitality Management",
          "custom_name": "",
          "course_name": "Diploma in Airlines, Tourism & Hospitality Management",
          "display_course_name": "Diploma in Airlines, Tourism & Hospitality Management",
          "total_current_fee": {
            "general": {
              "amount": 36000,
              "year": "2024 - 2025"
            }
          }
        },
        {
          "name": "Bakery And Confectionery",
          "custom_name": "",
          "course_name": "Diploma in Bakery and Confectionery",
          "display_course_name": "Diploma in Bakery and Confectionery",
          "total_current_fee": {
            "general": {
              "amount": 36000,
              "year": "2024 - 2025"
            }
          }
        },
        {
          "name": "Food Production",
          "custom_name": "",
          "course_name": "Diploma in Food Production",
          "display_course_name": "Diploma in Food Production",
          "total_current_fee": {
            "general": {
              "amount": 36000,
              "year": "2024 - 2025"
            }
          }
        }
      ],
      "eligibility": "10+2",
      "course_type": "Full Time",
      "degree_type": "Diploma",
      "short_head": "Diploma",
      "headone_data": {
        "headone": "diploma",
        "type": "Full Time"
      },
      "alumni_fees": [
        4000,
        4000,
        4000
      ],
      "total_fees": "36,000",
      "grand_total": "36,000"
    },
    {
      "course": "Master of Science [M.Sc] (Dietetics)",
      "level": "Post Graduation",
      "duration_year": "2",
      "duration_month": "0",
      "stream": [],
      "eligibility": "Graduation with 50%",
      "course_type": "Full Time",
      "degree_type": "Post Graduation",
      "short_head": "M.Sc",
      "headone_data": {
        "headone": "master-of-science-msc",
        "type": "Full Time"
      },
      "development_fees": [
        5000
      ],
      "alumni_fees": [
        4000
      ],
      "fees_per_year": "51,000",
      "grand_total": "93,000"
    }
  ]
}