{
  "basic_info": {
    "short_form": "National Power Training Institute Faridabad",
    "year_founded": 1965,
    "university_type": "",
    "type_of_college": "Public",
    "city": "Faridabad",
    "state": "Haryana",
    "address": {
      "address": "NPTI Complex, Sector 33 India",
      "location": "NPTI Complex, Sector 33,",
      "nearest_bus_station": {
        "name": "Ashoka Main",
        "lat": 28.46981,
        "lon": 77.31163,
        "place_id": "ChIJgyj45WrnDDkRcC0nW23NPRo",
        "distance": 1284,
        "eta": 316
      },
      "nearest_train_station": null,
      "nearest_airport": null,
      "map_location": "NPTI Complex, Sector 33 , Faridabad ,121003 Haryana",
      "pincode": "121003"
    },
    "landline": [
      {
        "value": "0129-2274916",
        "text": ""
      },
      {
        "value": 2274917,
        "text": ""
      }
    ],
    "mobile": [],
    "website": "https://npti.gov.in/contact-us",
    "phone_no": [
      {
        "value": "0129-2274916",
        "text": ""
      },
      {
        "value": 2274917,
        "text": ""
      },
      null
    ],
    "approved_by": [
      "AICTE"
    ],
    "major_stream_name": "Management",
    "affiliated_to": {
      "name": "JC Bose University, Faridabad"
    }
  },
  "courses": [
    {
      "course": "Post Graduate Diploma Course in Power Plant Engineering",
      "level": "Post Graduation",
      "duration_year": "1",
      "duration_month": "0",
      "stream": [],
      "eligibility": "B.E./B.Tech with 60%",
      "course_type": "Full Time",
      "degree_type": "Post Graduation",
      "short_head": "PG Diploma",
      "headone_data": {
        "headone": "post-graduate-diploma",
        "type": "Full Time"
      },
      "total_fees": "2.3 Lakhs",
      "grand_total": "2.3 Lakhs"
    },
    {
      "course": "Master of Business Administration [MBA] (Power Management)",
      "level": "Post Graduation",
      "duration_year": "2",
      "duration_month": "0",
      "stream": [],
      "eligibility": "GRADUATION with 60% CAT/GMAT",
      "course_type": "Full Time",
      "degree_type": "Post Graduation",
      "short_head": "MBA",
      "headone_data": {
        "headone": "master-of-business-administration-mba",
        "type": "Full Time"
      },
      "fees_per_year": "4.98 Lakhs",
      "grand_total": "9.96 Lakhs"
    }
  ]
}