{
  "basic_info": {
    "short_form": "Swami Devanand PG College Deoria",
    "year_founded": 1964,
    "university_type": "",
    "type_of_college": "Private",
    "city": "Deoria",
    "state": "Uttar Pradesh",
    "address": {
      "address": "Math-Lar Nearest Railway Station Salempur and Lar Road India",
      "location": "Math-Lar Nearest Railway Station Salempur and Lar Road",
      "nearest_bus_station": {
        "name": "Lar Bus Stand",
        "lat": 26.208546,
        "lon": 83.966905,
        "place_id": "ChIJ1YTHTi5KkjkRQXIkUhZ9KR8",
        "distance": 1022,
        "eta": 118
      },
      "nearest_train_station": null,
      "nearest_airport": null,
      "map_location": "Swami Devanand PG College, Deoria",
      "pincode": "274502"
    },
    "landline": [
      {
        "value": "05566-236325",
        "text": ""
      }
    ],
    "mobile": [
      "9336076028"
    ],
    "website": "http://www.sdpgmathlar.org",
    "phone_no": [
      {
        "value": "05566-236325",
        "text": ""
      },
      "9336076028"
    ],
    "approved_by": [
      "NCTE",
      "UGC"
    ],
    "major_stream_name": "Arts",
    "affiliated_to": {
      "name": "DDU, Gorakhpur"
    }
  },
  "courses": [
    {
      "course": "B.Sc",
      "level": "Graduation",
      "duration_year": "3",
      "duration_month": "0",
      "stream": [
        {
          "name": "Botany",
          "custom_name": "",
          "course_name": "Bachelor of Science [B.Sc] (Botany)",
          "display_course_name": "Bachelor of Science [B.Sc] (Botany)",
          "total_current_fee": {
            "general": {
              "amount": 10294,
              "year": ""
            }
          }
        },
        {
          "name": "Physics",
          "custom_name": "",
          "course_name": "Bachelor of Science [B.Sc] (Physics)",
          "display_course_name": "Bachelor of Science [B.Sc] (Physics)",
          "total_current_fee": {
            "general": {
              "amount": 10294,
              "year": ""
            }
          }
        },
        {
          "name": "Zoology",
          "custom_name": "",
          "course_name": "Bachelor of Science [B.Sc] (Zoology)",
          "display_course_name": "Bachelor of Science [B.Sc] (Zoology)",
          "total_current_fee": {
            "general": {
              "amount": 10294,
              "year": ""
            }
          }
        },
        {
          "name": "Biology",
          "custom_name": "",
          "course_name": "Bachelor of Science [B.Sc] (Biology)",
          "display_course_name": "Bachelor of Science [B.Sc] (Biology)",
          "total_current_fee": null
        },
        {
          "name": "Chemistry",
          "custom_name": "",
          "course_name": "Bachelor of Science [B.Sc] (Chemistry)",
          "display_course_name": "Bachelor of Science [B.Sc] (Chemistry)",
          "total_current_fee": {
            "general": {
              "amount": 10294,
              "year": ""
            }
          }
        },
        {
          "name": "Physical Education",
          "custom_name": "",
          "course_name": "Bachelor of Science [B.Sc] (Physical Education)",
          "display_course_name": "Bachelor of Science [B.Sc] (Physical Education)",
          "total_current_fee": null
        }
      ],
      "eligibility": "10+2",
      "course_type": "Full Time",
      "degree_type": "Degree",
      "short_head": "B.Sc",
      "headone_data": {
        "headone": "bachelor-of-science-bsc",
        "type": "Full Time"
      },
      "total_fees": "10,294",
      "grand_total": "10,294"
    },
    {
      "course": "BA",
      "level": "Graduation",
      "duration_year": "3",
      "duration_month": "0",
      "stream": [
        {
          "name": "Sanskrit",
          "custom_name": "",
          "course_name": "Bachelor of Arts [BA] (Sanskrit)",
          "display_course_name": "Bachelor of Arts [BA] (Sanskrit)",
          "total_current_fee": {
            "general": {
              "amount": 8132,
              "year": ""
            }
          }
        },
        {
          "name": "English",
          "custom_name": "",
          "course_name": "Bachelor of Arts [BA] (English)",
          "display_course_name": "Bachelor of Arts [BA] (English)",
          "total_current_fee": {
            "general": {
              "amount": 8132,
              "year": ""
            }
          }
        },
        {
          "name": "Home Science",
          "custom_name": "",
          "course_name": "Bachelor of Arts [BA] (Home Science)",
          "display_course_name": "Bachelor of Arts [BA] (Home Science)",
          "total_current_fee": null
        },
        {
          "name": "Geography",
          "custom_name": "",
          "course_name": "Bachelor of Arts [BA] (Geography)",
          "display_course_name": "Bachelor of Arts [BA] (Geography)",
          "total_current_fee": {
            "general": {
              "amount": 8132,
              "year": ""
            }
          }
        },
        {
          "name": "Hindi",
          "custom_name": "",
          "course_name": "Bachelor of Arts [BA] (Hindi)",
          "display_course_name": "Bachelor of Arts [BA] (Hindi)",
          "total_current_fee": {
            "general": {
              "amount": 8132,
              "year": ""
            }
          }
        },
        {
          "name": "Mathematics",
          "custom_name": "",
          "course_name": "Bachelor of Arts [BA] (Mathematics)",
          "display_course_name": "Bachelor of Arts [BA] (Mathematics)",
          "total_current_fee": {
            "general": {
              "amount": 8132,
              "year": ""
            }
          }
        },
        {
          "name": "Psychology",
          "custom_name": "",
          "course_name": "Bachelor of Arts [BA] (Psychology)",
          "display_course_name": "Bachelor of Arts [BA] (Psychology)",
          "total_current_fee": {
            "general": {
              "amount": 8132,
              "year": ""
            }
          }
        },
        {
          "name": "Philosophy",
          "custom_name": "",
          "course_name": "Bachelor of Arts [BA] (Philosophy)",
          "display_course_name": "Bachelor of Arts [BA] (Philosophy)",
          "total_current_fee": {
            "general": {
              "amount": 8132,
              "year": ""
            }
          }
        },
        {
          "name": "Economics",
          "custom_name": "",
          "course_name": "Bachelor of Arts [BA] (Economics)",
          "display_course_name": "Bachelor of Arts [BA] (Economics)",
          "total_current_fee": {
            "general": {
              "amount": 8132,
              "year": ""
            }
          }
        },
        {
          "name": "Ancient History",
          "custom_name": "",
          "course_name": "Bachelor of Arts [BA] (Ancient History)",
          "display_course_name": "Bachelor of Arts [BA] (Ancient History)",
          "total_current_fee": {
            "general": {
              "amount": 8132,
              "year": ""
            }
          }
        },
        {
          "name": "History",
          "custom_name": "",
          "course_name": "Bachelor of Arts [BA] (History)",
          "display_course_name": "Bachelor of Arts [BA] (History)",
          "total_current_fee": {
            "general": {
              "amount": 8132,
              "year": ""
            }
          }
        },
        {
          "name": "Physical Education",
          "custom_name": "",
          "course_name": "Bachelor of Arts [BA] (Physical Education)",
          "display_course_name": "Bachelor of Arts [BA] (Physical Education)",
          "total_current_fee": null
        },
        {
          "name": "Political Science",
          "custom_name": "",
          "course_name": "Bachelor of Arts [BA] (Political Science)",
          "display_course_name": "Bachelor of Arts [BA] (Political Science)",
          "total_current_fee": {
            "general": {
              "amount": 8132,
              "year": ""
            }
          }
        },
        {
          "name": "Sociology",
          "custom_name": "",
          "course_name": "Bachelor of Arts [BA] (Sociology)",
          "display_course_name": "Bachelor of Arts [BA] (Sociology)",
          "total_current_fee": {
            "general": {
              "amount": 8132,
              "year": ""
            }
          }
        }
      ],
      "eligibility": "10+2",
      "course_type": "Full Time",
      "degree_type": "Degree",
      "short_head": "BA",
      "headone_data": {
        "headone": "bachelor-of-arts-ba",
        "type": "Full Time"
      },
      "total_fees": "8,132",
      "grand_total": "8,132"
    },
    {
      "course": "MA",
      "level": "Post Graduation",
      "duration_year": "2",
      "duration_month": "0",
      "stream": [
        {
          "name": "Sociology",
          "custom_name": "",
          "course_name": "Master of Arts [MA] (Sociology)",
          "display_course_name": "Master of Arts [MA] (Sociology)",
          "total_current_fee": {
            "general": {
              "amount": 6780,
              "year": ""
            }
          }
        },
        {
          "name": "Political Science",
          "custom_name": "",
          "course_name": "Master of Arts [MA] (Political Science)",
          "display_course_name": "Master of Arts [MA] (Political Science)",
          "total_current_fee": {
            "general": {
              "amount": 6780,
              "year": ""
            }
          }
        },
        {
          "name": "Hindi",
          "custom_name": "",
          "course_name": "Master of Arts [MA] (Hindi)",
          "display_course_name": "Master of Arts [MA] (Hindi)",
          "total_current_fee": {
            "general": {
              "amount": 6780,
              "year": ""
            }
          }
        }
      ],
      "eligibility": "Graduation",
      "course_type": "Full Time",
      "degree_type": "Post Graduation",
      "short_head": "MA",
      "headone_data": {
        "headone": "master-of-arts-ma",
        "type": "Full Time"
      },
      "total_fees": "6,780",
      "grand_total": "6,780"
    }
  ]
}