{
  "basic_info": {
    "short_form": "School of Solar Energy Gandhinagar",
    "year_founded": 2007,
    "university_type": "",
    "type_of_college": "Private",
    "city": "Gandhinagar",
    "state": "Gujarat",
    "address": {
      "address": "Raisan Village India",
      "location": "Raisan Village, District-",
      "nearest_bus_station": {
        "name": "JA 6 Bus Station",
        "lat": 23.233215,
        "lon": 72.675178,
        "place_id": "ChIJp_JSjhIrXDkRbcGjhcPsb70",
        "distance": 863,
        "eta": 212
      },
      "nearest_train_station": null,
      "nearest_airport": null,
      "map_location": "School of Solar Energy , Gandhinagar",
      "pincode": "382007"
    },
    "landline": [
      {
        "value": "079-23275018",
        "text": ""
      },
      {
        "value": 23275012,
        "text": ""
      }
    ],
    "mobile": [],
    "website": "http://sse.pdpu.ac.in",
    "phone_no": [
      {
        "value": "079-23275018",
        "text": ""
      },
      {
        "value": 23275012,
        "text": ""
      },
      null
    ],
    "approved_by": [
      "AICTE"
    ],
    "major_stream_name": "Engineering",
    "affiliated_to": {
      "name": "PDPU, Gandhinagar"
    }
  },
  "courses": [
    {
      "course": "Master of Technology [M.Tech] (Electrical Energy Systems)",
      "level": "Post Graduation",
      "duration_year": "2",
      "duration_month": "0",
      "stream": [],
      "eligibility": "Pass in Graduation + GATE",
      "course_type": "Full Time",
      "degree_type": "Post Graduation",
      "short_head": "M.Tech",
      "headone_data": {
        "headone": "master-of-technology-mtech",
        "type": "Full Time"
      },
      "other_fee": [
        51500
      ],
      "fees_per_year": "1.62 Lakhs",
      "grand_total": "3.22 Lakhs"
    },
    {
      "course": "Ph.D",
      "level": "Doctorate/M.Phil",
      "duration_year": "2",
      "duration_month": "0",
      "stream": [],
      "eligibility": "Post Graduation",
      "course_type": "Full Time",
      "degree_type": "Degree",
      "short_head": "Ph.D",
      "headone_data": {
        "headone": "phd",
        "type": "Full Time"
      },
      "fees_per_year": "65,000",
      "grand_total": "1.15 Lakhs"
    }
  ]
}